MANIFEST.in
README.rst
setup.py
piereling/__init__.py
piereling/piereling.config.yml
piereling/piereling.py
piereling/piereling.wsgi
piereling/piereling_wrapper.py
piereling.egg-info/PKG-INFO
piereling.egg-info/SOURCES.txt
piereling.egg-info/dependency_links.txt
piereling.egg-info/requires.txt
piereling.egg-info/top_level.txt