Metadata-Version: 1.1
Name: piereling
Version: 0.2
Summary: Piereling is a webservice and web-application to convert between a variety of document formats, mostly from and to FoLiA XML. It is intended for NLP pipelines.
Home-page: https://github.com/proycon/piereling
Author: Maarten van Gompel
Author-email: UNKNOWN
License: GPL
Keywords: webservice nlp computational_linguistics rest folia conversion
Platform: UNKNOWN
Classifier: Development Status :: 5 - Production/Stable
Classifier: Topic :: Internet :: WWW/HTTP :: WSGI :: Application
Classifier: Topic :: Text Processing :: Linguistic
Classifier: Programming Language :: Python :: 3.4
Classifier: Programming Language :: Python :: 3.5
Classifier: Programming Language :: Python :: 3.6
Classifier: Programming Language :: Python :: 3.7
Classifier: Operating System :: POSIX
Classifier: Intended Audience :: Developers
Classifier: Intended Audience :: Science/Research
Classifier: License :: OSI Approved :: GNU General Public License v3 (GPLv3)
